[
  {
    "label": "Viblo Chrome extension",
    "size": "lg"
  },
  {
    "label": "Viblo Atom plugin",
    "size": "lg"
  },
  {
    "label": "Viblo SDK",
    "size": "lg"
  },
  {
    "label": "Viblo Smartphone app",
    "size": "lg"
  },
  {
    "label": "Web application",
    "size": "lg"
  },
  {
    "label": "Docker",
    "size": "sm"
  },
  {
    "label": "Postgres",
    "size": "sm"
  },
  {
    "label": "Mongodb",
    "size": "sm"
  },
  {
    "label": "Vue.js",
    "size": "sm"
  },
  {
    "label": "ELK stack",
    "size": "sm"
  }
]
